Workbook

Sheet Sales_Data
A1: Sales_ID | B1: Order_Date | C1: Customer_ID | D1: Customer_Name | E1: Product_ID | F1: Product_Name | G1: Category | H1: Quantity | I1: Unit_Price | J1: Total_Sales | K1: Employee_ID | L1: Employee_Names | M1: City | N1: Payment_Method | O1: Order_Status
A2: S001 | B2: 45662 | C2: C001 | D2: Customer_001 | E2: P001 | F2: Product_001 | G2: Electronics | H2: 2 | I2: 25000 | J2: 50000 | K2: EMP001 | L2: =_xlfn.XLOOKUP(K2,Employees!$A$2:$A$51,Employees!$B$2:$B$51) -> Arjun Kumar | M2: =_xlfn.XLOOKUP(K2,Employees!$A$2:$A$51,Employees!$E$2:$E$51) -> Chennai | N2: {=INDEX(Lookup!$C$2:$C$6,RANDBETWEEN(1,5))} -> Net Banking | O2: Delivery
A3: S002 | B3: 45663 | C3: C002 | D3: Customer_002 | E3: P002 | F3: Product_002 | G3: Clothing | H3: 3 | I3: 1500 | J3: 4500 | K3: EMP002 | L3: =_xlfn.XLOOKUP(K3,Employees!$A$2:$A$51,Employees!$B$2:$B$51) -> Priya Sharma | M3: =_xlfn.XLOOKUP(K3,Employees!$A$2:$A$51,Employees!$E$2:$E$51) -> Bangalore | N3: UPI | O3: Returned
A4: S003 | B4: 45664 | C4: C003 | D4: Customer_003 | E4: P003 | F4: Product_003 | G4: Grocery | H4: 5 | I4: 500 | J4: 2500 | K4: EMP003 | L4: =_xlfn.XLOOKUP(K4,Employees!$A$2:$A$51,Employees!$B$2:$B$51) -> Rahul Verma | M4: =_xlfn.XLOOKUP(K4,Employees!$A$2:$A$51,Employees!$E$2:$E$51) -> Hydrabed | N4: Net Banking | O4: Cancelled
A5: S004 | B5: 45665 | C5: C004 | D5: Customer_004 | E5: P004 | F5: Product_004 | G5: Furniture | H5: 1 | I5: 12000 | J5: 12000 | K5: EMP004 | L5: =_xlfn.XLOOKUP(K5,Employees!$A$2:$A$51,Employees!$B$2:$B$51) -> Sneha Reddy | M5: =_xlfn.XLOOKUP(K5,Employees!$A$2:$A$51,Employees!$E$2:$E$51) -> Chennai | N5: COD | O5: Returned
A6: S005 | B6: 45666 | C6: C005 | D6: Customer_005 | E6: P005 | F6: Product_005 | G6: Accessories | H6: 4 | I6: 800 | J6: 3200 | K6: EMP005 | L6: =_xlfn.XLOOKUP(K6,Employees!$A$2:$A$51,Employees!$B$2:$B$51) -> Karthik Raj | M6: =_xlfn.XLOOKUP(K6,Employees!$A$2:$A$51,Employees!$E$2:$E$51) -> Bangalore | N6: Cash | O6: Pending
A7: S006 | B7: 45667 | C7: C006 | D7: Customer_006 | E7: P006 | F7: Product_006 | G7: Electronics | H7: 2 | I7: 18000 | J7: 36000 | K7: EMP006 | L7: =_xlfn.XLOOKUP(K7,Employees!$A$2:$A$51,Employees!$B$2:$B$51) -> Divya Nair | M7: =_xlfn.XLOOKUP(K7,Employees!$A$2:$A$51,Employees!$E$2:$E$51) -> Hydrabed | N7: Cash | O7: Returned
A8: S007 | B8: 45668 | C8: C007 | D8: Customer_007 | E8: P007 | F8: Product_007 | G8: Clothing | H8: 2 | I8: 2200 | J8: 4400 | K8: EMP007 | L8: =_xlfn.XLOOKUP(K8,Employees!$A$2:$A$51,Employees!$B$2:$B$51) -> Ajay Singh | M8: =_xlfn.XLOOKUP(K8,Employees!$A$2:$A$51,Employees!$E$2:$E$51) -> Chennai | N8: Card | O8: Delivery
A9: S008 | B9: 45669 | C9: C008 | D9: Customer_008 | E9: P008 | F9: Product_008 | G9: Grocery | H9: 6 | I9: 300 | J9: 1800 | K9: EMP008 | L9: =_xlfn.XLOOKUP(K9,Employees!$A$2:$A$51,Employees!$B$2:$B$51) -> Meera Joshi | M9: =_xlfn.XLOOKUP(K9,Employees!$A$2:$A$51,Employees!$E$2:$E$51) -> Mumbai | N9: Card | O9: Pending
A10: S009 | B10: 45670 | C10: C009 | D10: Customer_009 | E10: P009 | F10: Product_009 | G10: Furniture | H10: 1 | I10: 15000 | J10: 15000 | K10: EMP009 | L10: =_xlfn.XLOOKUP(K10,Employees!$A$2:$A$51,Employees!$B$2:$B$51) -> Sanjay Kumar | M10: =_xlfn.XLOOKUP(K10,Employees!$A$2:$A$51,Employees!$E$2:$E$51) -> Delhi | N10: UPI | O10: Returned
A11: S010 | B11: 45671 | C11: C010 | D11: Customer_010 | E11: P010 | F11: Product_010 | G11: Accessories | H11: 3 | I11: 1200 | J11: 3600 | K11: EMP010 | L11: =_xlfn.XLOOKUP(K11,Employees!$A$2:$A$51,Employees!$B$2:$B$51) -> Pooja Patel | M11: =_xlfn.XLOOKUP(K11,Employees!$A$2:$A$51,Employees!$E$2:$E$51) -> Bangalore | N11: Card | O11: Cancelled
A12: S011 | B12: 45672 | C12: C011 | D12: Customer_011 | E12: P011 | F12: Product_011 | G12: Electronics | H12: 1 | I12: 32000 | J12: 32000 | K12: EMP011 | L12: =_xlfn.XLOOKUP(K12,Employees!$A$2:$A$51,Employees!$B$2:$B$51) -> Nithya Krishnan | M12: =_xlfn.XLOOKUP(K12,Employees!$A$2:$A$51,Employees!$E$2:$E$51) -> Chennai | N12: Cash | O12: Delivery
A13: S012 | B13: 45673 | C13: C012 | D13: Customer_012 | E13: P012 | F13: Product_012 | G13: Clothing | H13: 4 | I13: 1800 | J13: 7200 | K13: EMP012 | L13: =_xlfn.XLOOKUP(K13,Employees!$A$2:$A$51,Employees!$B$2:$B$51) -> Rohit Mehta | M13: =_xlfn.XLOOKUP(K13,Employees!$A$2:$A$51,Employees!$E$2:$E$51) -> Hydrabed | N13: Cash | O13: Delivery
A14: S013 | B14: 45674 | C14: C013 | D14: Customer_013 | E14: P013 | F14: Product_013 | G14: Grocery | H14: 8 | I14: 250 | J14: 2000 | K14: EMP013 | L14: =_xlfn.XLOOKUP(K14,Employees!$A$2:$A$51,Employees!$B$2:$B$51) -> Aisha Khan | M14: =_xlfn.XLOOKUP(K14,Employees!$A$2:$A$51,Employees!$E$2:$E$51) -> Delhi | N14: UPI | O14: Pending
... A478: S477 | B478: 46139 | C478: C477 | D478: Customer_477 | E478: P007 | F478: Product_007 | G478: Clothing | H478: 4 | I478: 2200 | J478: 8800 | K478: EMP017 | L478: =_xlfn.XLOOKUP(K478,Employees!$A$2:$A$51,Employees!$B$2:$B$51) -> Lakshmi Devi | M478: =_xlfn.XLOOKUP(K478,Employees!$A$2:$A$51,Employees!$E$2:$E$51) -> Bangalore | N478: Card | O478: Returned
A479: S478 | B479: 46140 | C479: C478 | D479: Customer_478 | E479: P008 | F479: Product_008 | G479: Grocery | H479: 5 | I479: 300 | J479: 1500 | K479: EMP018 | L479: =_xlfn.XLOOKUP(K479,Employees!$A$2:$A$51,Employees!$B$2:$B$51) -> Mohammed Ali | M479: =_xlfn.XLOOKUP(K479,Employees!$A$2:$A$51,Employees!$E$2:$E$51) -> Hydrabed | N479: Net Banking | O479: Pending | S479: =S479 -> 0
A480: S479 | B480: 46141 | C480: C479 | D480: Customer_479 | E480: P009 | F480: Product_009 | G480: Furniture | H480: 2 | I480: 15000 | J480: 30000 | K480: EMP019 | L480: =_xlfn.XLOOKUP(K480,Employees!$A$2:$A$51,Employees!$B$2:$B$51) -> Kavya Srinivas | M480: =_xlfn.XLOOKUP(K480,Employees!$A$2:$A$51,Employees!$E$2:$E$51) -> Delhi | N480: COD | O480: Pending
A481: S480 | B481: 46142 | C481: C480 | D481: Customer_480 | E481: P010 | F481: Product_010 | G481: Accessories | H481: 3 | I481: 1200 | J481: 3600 | K481: EMP020 | L481: =_xlfn.XLOOKUP(K481,Employees!$A$2:$A$51,Employees!$B$2:$B$51) -> Rakesh Sharma | M481: =_xlfn.XLOOKUP(K481,Employees!$A$2:$A$51,Employees!$E$2:$E$51) -> Mumbai | N481: Net Banking | O481: Delivery
A482: S481 | B482: 46143 | C482: C481 | D482: Customer_481 | E482: P011 | F482: Product_011 | G482: Electronics | H482: 2 | I482: 32000 | J482: 64000 | K482: EMP001 | L482: =_xlfn.XLOOKUP(K482,Employees!$A$2:$A$51,Employees!$B$2:$B$51) -> Arjun Kumar | M482: =_xlfn.XLOOKUP(K482,Employees!$A$2:$A$51,Employees!$E$2:$E$51) -> Chennai | N482: Net Banking | O482: Cancelled
A483: S482 | B483: 46144 | C483: C482 | D483: Customer_482 | E483: P012 | F483: Product_012 | G483: Clothing | H483: 1 | I483: 1800 | J483: 1800 | K483: EMP002 | L483: =_xlfn.XLOOKUP(K483,Employees!$A$2:$A$51,Employees!$B$2:$B$51) -> Priya Sharma | M483: =_xlfn.XLOOKUP(K483,Employees!$A$2:$A$51,Employees!$E$2:$E$51) -> Bangalore | N483: COD | O483: Delivery
A484: S483 | B484: 46145 | C484: C483 | D484: Customer_483 | E484: P013 | F484: Product_013 | G484: Grocery | H484: 6 | I484: 250 | J484: 1500 | K484: EMP003 | L484: =_xlfn.XLOOKUP(K484,Employees!$A$2:$A$51,Employees!$B$2:$B$51) -> Rahul Verma | M484: =_xlfn.XLOOKUP(K484,Employees!$A$2:$A$51,Employees!$E$2:$E$51) -> Hydrabed | N484: Net Banking | O484: Delivery
A485: S484 | B485: 46146 | C485: C484 | D485: Customer_484 | E485: P014 | F485: Product_014 | G485: Furniture | H485: 2 | I485: 9000 | J485: 18000 | K485: EMP004 | L485: =_xlfn.XLOOKUP(K485,Employees!$A$2:$A$51,Employees!$B$2:$B$51) -> Sneha Reddy | M485: =_xlfn.XLOOKUP(K485,Employees!$A$2:$A$51,Employees!$E$2:$E$51) -> Chennai | N485: Cash | O485: Delivery
A486: S485 | B486: 46147 | C486: C485 | D486: Customer_485 | E486: P015 | F486: Product_015 | G486: Accessories | H486: 4 | I486: 600 | J486: 2400 | K486: EMP005 | L486: =_xlfn.XLOOKUP(K486,Employees!$A$2:$A$51,Employees!$B$2:$B$51) -> Karthik Raj | M486: =_xlfn.XLOOKUP(K486,Employees!$A$2:$A$51,Employees!$E$2:$E$51) -> Bangalore | N486: Card | O486: Delivery
A487: S486 | B487: 46148 | C487: C486 | D487: Customer_486 | E487: P016 | F487: Product_016 | G487: Electronics | H487: 3 | I487: 21000 | J487: 63000 | K487: EMP006 | L487: =_xlfn.XLOOKUP(K487,Employees!$A$2:$A$51,Employees!$B$2:$B$51) -> Divya Nair | M487: =_xlfn.XLOOKUP(K487,Employees!$A$2:$A$51,Employees!$E$2:$E$51) -> Hydrabed | N487: UPI | O487: Pending
A488: S487 | B488: 46149 | C488: C487 | D488: Customer_487 | E488: P017 | F488: Product_017 | G488: Clothing | H488: 2 | I488: 2500 | J488: 5000 | K488: EMP007 | L488: =_xlfn.XLOOKUP(K488,Employees!$A$2:$A$51,Employees!$B$2:$B$51) -> Ajay Singh | M488: =_xlfn.XLOOKUP(K488,Employees!$A$2:$A$51,Employees!$E$2:$E$51) -> Chennai | N488: COD | O488: Returned
A489: S488 | B489: 46150 | C489: C488 | D489: Customer_488 | E489: P018 | F489: Product_018 | G489: Grocery | H489: 8 | I489: 700 | J489: 5600 | K489: EMP008 | L489: =_xlfn.XLOOKUP(K489,Employees!$A$2:$A$51,Employees!$B$2:$B$51) -> Meera Joshi | M489: =_xlfn.XLOOKUP(K489,Employees!$A$2:$A$51,Employees!$E$2:$E$51) -> Mumbai | N489: COD | O489: Delivery
A490: S489 | B490: 46151 | C490: C489 | D490: Customer_489 | E490: P019 | F490: Product_019 | G490: Furniture | H490: 1 | I490: 18000 | J490: 18000 | K490: EMP009 | L490: =_xlfn.XLOOKUP(K490,Employees!$A$2:$A$51,Employees!$B$2:$B$51) -> Sanjay Kumar | M490: =_xlfn.XLOOKUP(K490,Employees!$A$2:$A$51,Employees!$E$2:$E$51) -> Delhi | N490: COD | O490: Pending
A491: S490 | B491: 46152 | C491: C490 | D491: Customer_490 | E491: P020 | F491: Product_020 | G491: Accessories | H491: 5 | I491: 900 | J491: 4500 | K491: EMP010 | L491: =_xlfn.XLOOKUP(K491,Employees!$A$2:$A$51,Employees!$B$2:$B$51) -> Pooja Patel | M491: =_xlfn.XLOOKUP(K491,Employees!$A$2:$A$51,Employees!$E$2:$E$51) -> Bangalore | N491: Cash | O491: Returned
... A501: S500 | B501: 46162 | C501: C500 | D501: Customer_500 | E501: P030 | F501: Product_030 | G501: Accessories | H501: 6 | I501: 500 | J501: 3000 | K501: EMP020 | L501: =_xlfn.XLOOKUP(K501,Employees!$A$2:$A$51,Employees!$B$2:$B$51) -> Rakesh Sharma | M501: =_xlfn.XLOOKUP(K501,Employees!$A$2:$A$51,Employees!$E$2:$E$51) -> Mumbai | N501: Net Banking | O501: Delivery

Sheet Employees
A1: Employee_ID | B1: Employee_Name | C1: Department | D1: Designation | E1: City | F1: Salary | G1: Joining_Date | H1: Manager
A2: EMP001 | B2: Arjun Kumar | C2: Sales | D2: Sales Executive | E2: Chennai | F2: 35000 | G2: 44941 | H2: Rajesh Kumar
A3: EMP002 | B3: Priya Sharma | C3: HR | D3: HR Executive | E3: Bangalore | F3: 40000 | G3: 44640 | H3: Anita Roy
A4: EMP003 | B4: Rahul Verma | C4: Finace | D4: Accountant | E4: Hydrabed | F4: 45000 | G4: 44387 | H4: Suesh Patel
A5: EMP004 | B5: Sneha Reddy | C5: Marketing | D5: Marketing Executive | E5: Chennai | F5: 38000 | G5: 45174 | H5: Kavitha Naire
A6: EMP005 | B6: Karthik Raj | C6: IT | D6: Softwer Engineer | E6: Bangalore | F6: 55000 | G6: 44883 | H6: Vivek Menon
A7: EMP006 | B7: Divya Nair | C7: Sales | D7: Sales Executive | E7: Hydrabed | F7: 36000 | G7: 45334 | H7: Rajesh Kumar
A8: EMP007 | B8: Ajay Singh | C8: IT | D8: System Administrator | E8: Chennai | F8: 50000 | G8: 44416 | H8: Vivek Menon
A9: EMP008 | B9: Meera Joshi | C9: HR | D9: HR Manager | E9: Mumbai | F9: 60000 | G9: 43935 | H9: Anita Roy
A10: EMP009 | B10: Sanjay Kumar | C10: Finace | D10: Finace Analyst | E10: Delhi | F10: 48000 | G10: 44737 | H10: Suesh Patel
A11: EMP010 | B11: Pooja Patel | C11: Marketing | D11: Marketing Manager | E11: Bangalore | F11: 62000 | G11: 44499 | H11: Kavitha Naire
A12: EMP011 | B12: Nithya Krishnan | C12: Sales | D12: Sales Manager | E12: Chennai | F12: 65000 | G12: 43841 | H12: Rajesh Kumar
A13: EMP012 | B13: Rohit Mehta | C13: IT | D13: Sotwer Engineer | E13: Hydrabed | F13: 58000 | G13: 44823 | H13: Vivek Menon
... A21: EMP020 | B21: Rakesh Sharma | C21: HR | D21: Talent Acquisition Specialist | E21: Mumbai | F21: 46000 | G21: 44570 | H21: Anita Roy

Sheet Products
A1: Product_ID | B1: Product_Name | C1: Category | D1: Brand | E1: Unit_Price | F1: Stock | G1: Supplier
A2: P001 | B2: Laptop | C2: Electronics | D2: Dell | E2: 55000 | F2: 40 | G2: Tech Distributors
A3: P002 | B3: SmartPhone | C3: Electronics | D3: Samsung | E3: 28000 | F3: 60 | G3: Mobile World
A4: P003 | B4: HeadPhone | C4: Electronics | D4: Sony | E4: 3500 | F4: 100 | G4: Audio Hub
A5: P004 | B5: Office Chair | C5: Furniture | D5: Nikamal | E5: 6500 | F5: 25 | G5: Comfort Furniture
A6: P005 | B6: Study Table | C6: Furniture | D6: IKEA | E6: 8500 | F6: 20 | G6: Home Solutions
A7: P006 | B7: T-Shirt | C7: Clothing | D7: Puma | E7: 1200 | F7: 150 | G7: Fashion Zone
A8: P007 | B8: Jeans | C8: Clothing | D8: Levi's | E8: 2500 | F8: 90 | G8: Fashion Zone
A9: P008 | B9: Rice 10kg | C9: Grocery | D9: India Gate | E9: 900 | F9: 80 | G9: Fresh Mart
A10: P009 | B10: Cooking Oil 5L | C10: Grocery | D10: Fortune | E10: 1100 | F10: 70 | G10: Fresh Mart
A11: P010 | B11: Smart Watch | C11: Electronics | D11: Noice | E11: 4500 | F11: 50 | G11: Tech Distributors
A12: P011 | B12: Bluetooth Speaker | C12: Electronics | D12: JBl | E12: 4500 | F12: 45 | G12: Audio Hub
A13: P012 | B13: Keyboard | C13: Electronics | D13: Logitech | E13: 1800 | F13: 75 | G13: Tech Distributors
... A31: P030 | B31: Webcam | C31: Electronics | D31: Logitech | E31: 3500 | F31: 60 | G31: Tech Distributors

Sheet Customers
A1: Customer_ID | B1: Customer_Name | C1: Gender | D1: Age | E1: City | F1: State | G1: Phone | H1: Email
A2: C001 | B2: Aditya Kumar | C2: Male | D2: 28 | E2: Chennai | F2: Tamil Nadu | G2: 9876501001 | H2: aditya.kumar@gmail.com
A3: C002 | B3: Ananya Sharma | C3: Female | D3: 25 | E3: Bangalore | F3: Karnataka | G3: 9876501002 | H3: ananya.sharma@gmail.com
A4: C003 | B4: Rohit Verma | C4: Male | D4: 32 | E4: Hyderabed | F4: Telengana | G4: 9876501003 | H4: rohit.verma@gmail.com
A5: C004 | B5: Sneha Reddy | C5: Female | D5: 29 | E5: Chennai | F5: Tamil Nadu | G5: 9876501004 | H5: sneha.reddy@gmail.com
A6: C005 | B6: Vikram Singh | C6: Male | D6: 35 | E6: Delhi | F6: Delhi | G6: 9876501005 | H6: vikram.singh@gmail.com
A7: C006 | B7: Priya Naire | C7: Female | D7: 27 | E7: Mumbai | F7: Maharashtra | G7: 9876501006 | H7: priya.nair@gmail.com
A8: C007 | B8: Arjun Patel | C8: Male | D8: 41 | E8: Ahmedabad | F8: Gujarat | G8: 9876501007 | H8: arjun.patel@gmail.com
A9: C008 | B9: Meera Iyer | C9: Female | D9: 30 | E9: Chennai | F9: Tamil Nadu | G9: 9876501008 | H9: meera.iyer@gmail.com
A10: C009 | B10: Karan Mehata | C10: Male | D10: 26 | E10: Bangalore | F10: Karnataka | G10: 9876501009 | H10: karan.mehata@gmail.com
A11: C010 | B11: Divya Krishnan | C11: Female | D11: 33 | E11: Hyderabed | F11: Talengana | G11: 9876501010 | H11: divya.krishnan@gmail.com
A12: C011 | B12: Nikhil Rao | C12: Male | D12: 38 | E12: Pune | F12: Maharashtra | G12: 9876501011 | H12: nikhil.rao@gmail.com
A13: C012 | B13: Kavya Menon | C13: Female | D13: 24 | E13: Kochi | F13: Kerla | G13: 9876501012 | H13: kavya.menon@gmail.com
... A101: C100 | B101: Anjali Kumar | C101: Female | D101: 33 | E101: Chennai | F101: Tamil Nadu | G101: 9876501100 | H101: anjali.kumar@gmail.com

Sheet Dashboard
A1: Toatal Sales | B1: Total Orders | C1: Average Sales | D1: Total Quntity
A2: =SUM(Sales_Data!J2:J501) -> 7850300 | B2: =COUNTA(Sales_Data!A2:A501) -> 500 | C2: =AVERAGE(Sales_Data!J2:J501) -> 15700.6 | D2: =SUM(Sales_Data!H2:H501) -> 1693
A4: Category | B4: Sales | D4: City | E4: Sales | G4: Payment Method | H4: Ordes | J4: Order Status | K4: Count
A5: Electronics | B5: =SUMIF(Sales_Data!G:G,A5,Sales_Data!J:J) -> 4809000 | D5: Chennai | E5: =SUMIF(Sales_Data!M:M,D5,Sales_Data!J:J) -> 4012000 | G5: UPI | H5: =COUNTIF(Sales_Data!N:N,G5) -> 106 | J5: Delivery | K5: =COUNTIF(Sales_Data!O:O,J5) -> 0
A6: Clothing | B6: =SUMIF(Sales_Data!G:G,A6,Sales_Data!J:J) -> 516400 | D6: Bangalore | E6: =SUMIF(Sales_Data!M:M,D6,Sales_Data!J:J) -> 763800 | G6: Card | H6: =COUNTIF(Sales_Data!N:N,G6) -> 111 | J6: Pending | K6: =COUNTIF(Sales_Data!O:O,J6) -> 132
A7: furniture | B7: =SUMIF(Sales_Data!G:G,A7,Sales_Data!J:J) -> 1898000 | D7: Hydrabed | E7: =SUMIF(Sales_Data!M:M,D7,Sales_Data!J:J) -> 1548500 | G7: Cash | H7: =COUNTIF(Sales_Data!N:N,G7) -> 85 | J7: Cancelled | K7: =COUNTIF(Sales_Data!O:O,J7) -> 111
A8: Accessories | B8: =SUMIF(Sales_Data!G:G,A8,Sales_Data!J:J) -> 314000 | D8: Delhi | E8: =SUMIF(Sales_Data!M:M,D8,Sales_Data!J:J) -> 1288600 | G8: Net Banking | H8: =COUNTIF(Sales_Data!N:N,G8) -> 96 | J8: Returned | K8: =COUNTIF(Sales_Data!O:O,J8) -> 118
A9: Grocery | B9: =SUMIF(Sales_Data!G:G,A9,Sales_Data!J:J) -> 312900 | D9: Mubai | E9: =SUMIF(Sales_Data!M:M,D9,Sales_Data!J:J) -> 0

Sheet Lookup
A1: Department | B1: Categories | C1: Payment_Method | D1: Order_Status
A2: Sales | B2: Electronics | C2: Cash | D2: Delivery
A3: HR | B3: Clothing | C3: UPI | D3: Pending
A4: Finance | B4: Grocery | C4: Card | D4: Cancelled
A5: Marketing | B5: Furniture | C5: Net Banking | D5: Returned
A6: IT | B6: Accessories | C6: COD | D6: Processing
